LICENSE
MANIFEST.in
setup.py
TracAdvancedSearch.egg-info/PKG-INFO
TracAdvancedSearch.egg-info/SOURCES.txt
TracAdvancedSearch.egg-info/dependency_links.txt
TracAdvancedSearch.egg-info/entry_points.txt
TracAdvancedSearch.egg-info/requires.txt
TracAdvancedSearch.egg-info/top_level.txt
solr/conf/data-config.xml
solr/conf/schema.xml
solr/conf/solrconfig.xml
tracadvsearch/__init__.py
tracadvsearch/advsearch.py
tracadvsearch/backend.py
tracadvsearch/interface.py
tracadvsearch/htdocs/css/advsearch.css
tracadvsearch/htdocs/css/pikaday.css
tracadvsearch/htdocs/js/advsearch.js
tracadvsearch/htdocs/js/pikaday.js
tracadvsearch/templates/advsearch.html