Metadata-Version: 1.1
Name: TracAdvancedSearch
Version: 0.6.0
Summary: This plugin allows you to index your wiki and ticket data in a full text search engine and search it from a button in the main navbar.
Home-page: http://github.com/dnephin/TracAdvancedSearchPlugin
Author: Daniel Nephin
Author-email: dnephin@gmail.com
License: SEE LICENSE
Keywords: trac,plugin,search,full-text-search
Platform: linux
Platform: osx
Platform: unix
Platform: win32
Classifier: Framework :: Trac
Classifier: Development Status :: 4 - Beta
Classifier: Environment :: Web Environment
Classifier: Intended Audience :: Developers
Classifier: Operating System :: OS Independent
Classifier: Programming Language :: Python
Classifier: Topic :: Software Development
